{
  "orders": [
    {
      "orderId": "ORD-0001",
      "customer": {
        "id": 1,
        "name": "Valerie Braun",
        "email": "name.jones@gmail.com",
        "phone": "1-638-705-7017 x89318"
      },
      "items": [
        {
          "sku": "SKU-OOH73G",
          "name": "Wireless Mouse",
          "quantity": 1,
          "price": 96.17
        }
      ],
      "subtotal": 96.17,
      "tax": 7.69,
      "total": 103.86,
      "status": "pending",
      "orderDate": "2026-01-20"
    },
    {
      "orderId": "ORD-0002",
      "customer": {
        "id": 2,
        "name": "Debbie O'Kon I",
        "email": "matteo_spencer@gmail.com",
        "phone": "275-549-9496"
      },
      "items": [
        {
          "sku": "SKU-QLVGD2",
          "name": "Wireless Mouse",
          "quantity": 1,
          "price": 27.27
        },
        {
          "sku": "SKU-CMR28H",
          "name": "USB Cable",
          "quantity": 1,
          "price": 28.45
        }
      ],
      "subtotal": 55.72,
      "tax": 4.46,
      "total": 60.18,
      "status": "processing",
      "orderDate": "2025-11-20"
    },
    {
      "orderId": "ORD-0003",
      "customer": {
        "id": 3,
        "name": "Lindsey Medhurst",
        "email": "gaetano_kuhlman49@hotmail.com",
        "phone": "(474) 419-2034 x31649"
      },
      "items": [
        {
          "sku": "SKU-HCMCCH",
          "name": "Wireless Mouse",
          "quantity": 3,
          "price": 118.24
        },
        {
          "sku": "SKU-GVVWWJ",
          "name": "USB Cable",
          "quantity": 4,
          "price": 87.53
        }
      ],
      "subtotal": 704.84,
      "tax": 56.39,
      "total": 761.23,
      "status": "shipped",
      "orderDate": "2026-01-06"
    },
    {
      "orderId": "ORD-0004",
      "customer": {
        "id": 4,
        "name": "Edmond Douglas-Tremblay",
        "email": "demetris.hoeger-pollich@yahoo.com",
        "phone": "477.332.6573"
      },
      "items": [
        {
          "sku": "SKU-MBKYWA",
          "name": "Wireless Mouse",
          "quantity": 2,
          "price": 168.98
        },
        {
          "sku": "SKU-BPSHD9",
          "name": "USB Cable",
          "quantity": 3,
          "price": 71.02
        },
        {
          "sku": "SKU-LFKNKQ",
          "name": "Laptop Stand",
          "quantity": 4,
          "price": 124.67
        }
      ],
      "subtotal": 1049.7,
      "tax": 83.98,
      "total": 1133.68,
      "status": "delivered",
      "orderDate": "2026-01-29"
    },
    {
      "orderId": "ORD-0005",
      "customer": {
        "id": 5,
        "name": "Henry Bergnaum",
        "email": "katelin.koepp22@yahoo.com",
        "phone": "638.598.2652 x8019"
      },
      "items": [
        {
          "sku": "SKU-P5PZC7",
          "name": "Wireless Mouse",
          "quantity": 3,
          "price": 130.4
        }
      ],
      "subtotal": 391.2,
      "tax": 31.3,
      "total": 422.5,
      "status": "cancelled",
      "orderDate": "2025-12-29"
    },
    {
      "orderId": "ORD-0006",
      "customer": {
        "id": 6,
        "name": "Pat Gulgowski",
        "email": "rick78@yahoo.com",
        "phone": "317.739.5613 x1123"
      },
      "items": [
        {
          "sku": "SKU-LNUS2O",
          "name": "Wireless Mouse",
          "quantity": 1,
          "price": 140.9
        },
        {
          "sku": "SKU-P7HZCB",
          "name": "USB Cable",
          "quantity": 3,
          "price": 127.68
        },
        {
          "sku": "SKU-SVJUWG",
          "name": "Laptop Stand",
          "quantity": 1,
          "price": 64.95
        }
      ],
      "subtotal": 588.89,
      "tax": 47.11,
      "total": 636,
      "status": "pending",
      "orderDate": "2025-12-19"
    },
    {
      "orderId": "ORD-0007",
      "customer": {
        "id": 7,
        "name": "Micheal Hane",
        "email": "jake64@gmail.com",
        "phone": "(754) 620-7242 x33679"
      },
      "items": [
        {
          "sku": "SKU-YWKM7O",
          "name": "Wireless Mouse",
          "quantity": 5,
          "price": 84.32
        },
        {
          "sku": "SKU-LVTXV7",
          "name": "USB Cable",
          "quantity": 3,
          "price": 136.84
        },
        {
          "sku": "SKU-JUF43V",
          "name": "Laptop Stand",
          "quantity": 1,
          "price": 194.28
        },
        {
          "sku": "SKU-5OO534",
          "name": "Keyboard",
          "quantity": 1,
          "price": 83.05
        }
      ],
      "subtotal": 1109.45,
      "tax": 88.76,
      "total": 1198.21,
      "status": "processing",
      "orderDate": "2025-11-23"
    },
    {
      "orderId": "ORD-0008",
      "customer": {
        "id": 8,
        "name": "Belinda Friesen",
        "email": "cleora.lang1@hotmail.com",
        "phone": "1-993-906-4512 x7507"
      },
      "items": [
        {
          "sku": "SKU-KDOKXM",
          "name": "Wireless Mouse",
          "quantity": 5,
          "price": 86.77
        },
        {
          "sku": "SKU-8OWOCM",
          "name": "USB Cable",
          "quantity": 4,
          "price": 27.99
        },
        {
          "sku": "SKU-RRYH4T",
          "name": "Laptop Stand",
          "quantity": 1,
          "price": 92.24
        }
      ],
      "subtotal": 638.05,
      "tax": 51.04,
      "total": 689.09,
      "status": "shipped",
      "orderDate": "2025-12-04"
    },
    {
      "orderId": "ORD-0009",
      "customer": {
        "id": 9,
        "name": "Emanuel Littel",
        "email": "jude26@hotmail.com",
        "phone": "968-718-4367"
      },
      "items": [
        {
          "sku": "SKU-3RP0TU",
          "name": "Wireless Mouse",
          "quantity": 4,
          "price": 169.06
        },
        {
          "sku": "SKU-0ZXEUO",
          "name": "USB Cable",
          "quantity": 5,
          "price": 85.28
        },
        {
          "sku": "SKU-BD7CUX",
          "name": "Laptop Stand",
          "quantity": 2,
          "price": 168.29
        },
        {
          "sku": "SKU-ZH4B1J",
          "name": "Keyboard",
          "quantity": 2,
          "price": 124.3
        }
      ],
      "subtotal": 1687.82,
      "tax": 135.03,
      "total": 1822.85,
      "status": "delivered",
      "orderDate": "2026-01-03"
    },
    {
      "orderId": "ORD-0010",
      "customer": {
        "id": 10,
        "name": "Patty Senger",
        "email": "libby_thompson37@hotmail.com",
        "phone": "(486) 952-8753 x3037"
      },
      "items": [
        {
          "sku": "SKU-DEE28P",
          "name": "Wireless Mouse",
          "quantity": 5,
          "price": 62.65
        },
        {
          "sku": "SKU-LMSGKQ",
          "name": "USB Cable",
          "quantity": 1,
          "price": 13.42
        },
        {
          "sku": "SKU-QRUBXW",
          "name": "Laptop Stand",
          "quantity": 3,
          "price": 10.69
        },
        {
          "sku": "SKU-UOYREK",
          "name": "Keyboard",
          "quantity": 3,
          "price": 129.49
        }
      ],
      "subtotal": 747.21,
      "tax": 59.78,
      "total": 806.99,
      "status": "cancelled",
      "orderDate": "2026-01-24"
    },
    {
      "orderId": "ORD-0011",
      "customer": {
        "id": 11,
        "name": "Naomi Koss",
        "email": "rachelle_feil50@yahoo.com",
        "phone": "635.414.6560 x4473"
      },
      "items": [
        {
          "sku": "SKU-7XO7J5",
          "name": "Wireless Mouse",
          "quantity": 3,
          "price": 116.57
        },
        {
          "sku": "SKU-QQC6KX",
          "name": "USB Cable",
          "quantity": 3,
          "price": 181.26
        },
        {
          "sku": "SKU-YYV5Y1",
          "name": "Laptop Stand",
          "quantity": 3,
          "price": 175.39
        },
        {
          "sku": "SKU-KY4TA8",
          "name": "Keyboard",
          "quantity": 1,
          "price": 29.47
        }
      ],
      "subtotal": 1449.13,
      "tax": 115.93,
      "total": 1565.06,
      "status": "pending",
      "orderDate": "2026-02-03"
    },
    {
      "orderId": "ORD-0012",
      "customer": {
        "id": 12,
        "name": "Sheri Prohaska",
        "email": "viva.paucek@gmail.com",
        "phone": "1-289-297-2320"
      },
      "items": [
        {
          "sku": "SKU-HNQBVK",
          "name": "Wireless Mouse",
          "quantity": 1,
          "price": 87.59
        },
        {
          "sku": "SKU-Z1JOQU",
          "name": "USB Cable",
          "quantity": 3,
          "price": 117.06
        }
      ],
      "subtotal": 438.77,
      "tax": 35.1,
      "total": 473.87,
      "status": "processing",
      "orderDate": "2026-01-05"
    },
    {
      "orderId": "ORD-0013",
      "customer": {
        "id": 13,
        "name": "Raymond Hansen",
        "email": "trace31@hotmail.com",
        "phone": "1-650-890-7922 x8314"
      },
      "items": [
        {
          "sku": "SKU-IGALAV",
          "name": "Wireless Mouse",
          "quantity": 3,
          "price": 77.57
        },
        {
          "sku": "SKU-2QANE4",
          "name": "USB Cable",
          "quantity": 5,
          "price": 196.3
        }
      ],
      "subtotal": 1214.21,
      "tax": 97.14,
      "total": 1311.35,
      "status": "shipped",
      "orderDate": "2025-11-24"
    },
    {
      "orderId": "ORD-0014",
      "customer": {
        "id": 14,
        "name": "Tamara Kerluke",
        "email": "jacinto67@yahoo.com",
        "phone": "228.961.1536 x54686"
      },
      "items": [
        {
          "sku": "SKU-MFZIHA",
          "name": "Wireless Mouse",
          "quantity": 3,
          "price": 98.3
        },
        {
          "sku": "SKU-KWDBNR",
          "name": "USB Cable",
          "quantity": 1,
          "price": 133.36
        },
        {
          "sku": "SKU-TNDHLZ",
          "name": "Laptop Stand",
          "quantity": 3,
          "price": 87.86
        }
      ],
      "subtotal": 691.84,
      "tax": 55.35,
      "total": 747.19,
      "status": "delivered",
      "orderDate": "2025-12-23"
    },
    {
      "orderId": "ORD-0015",
      "customer": {
        "id": 15,
        "name": "Lamar Gibson",
        "email": "linwood_senger@yahoo.com",
        "phone": "(799) 625-4666 x090"
      },
      "items": [
        {
          "sku": "SKU-3M4Y3J",
          "name": "Wireless Mouse",
          "quantity": 1,
          "price": 73.33
        },
        {
          "sku": "SKU-FTN0CC",
          "name": "USB Cable",
          "quantity": 5,
          "price": 69.83
        }
      ],
      "subtotal": 422.48,
      "tax": 33.8,
      "total": 456.28,
      "status": "cancelled",
      "orderDate": "2026-01-07"
    },
    {
      "orderId": "ORD-0016",
      "customer": {
        "id": 16,
        "name": "Carmen Pouros I",
        "email": "frederik57@hotmail.com",
        "phone": "(430) 789-2484 x70003"
      },
      "items": [
        {
          "sku": "SKU-QUC8VD",
          "name": "Wireless Mouse",
          "quantity": 3,
          "price": 167.88
        },
        {
          "sku": "SKU-QO4VIK",
          "name": "USB Cable",
          "quantity": 3,
          "price": 40.54
        }
      ],
      "subtotal": 625.26,
      "tax": 50.02,
      "total": 675.28,
      "status": "pending",
      "orderDate": "2025-12-26"
    },
    {
      "orderId": "ORD-0017",
      "customer": {
        "id": 17,
        "name": "Jennifer Leffler",
        "email": "maryjane.wiegand@yahoo.com",
        "phone": "1-623-926-5086 x6635"
      },
      "items": [
        {
          "sku": "SKU-3KRCKX",
          "name": "Wireless Mouse",
          "quantity": 1,
          "price": 137.43
        }
      ],
      "subtotal": 137.43,
      "tax": 10.99,
      "total": 148.42,
      "status": "processing",
      "orderDate": "2025-12-11"
    },
    {
      "orderId": "ORD-0018",
      "customer": {
        "id": 18,
        "name": "Dennis Wunsch",
        "email": "oral.hand90@hotmail.com",
        "phone": "258.778.1039 x5229"
      },
      "items": [
        {
          "sku": "SKU-AEDRDG",
          "name": "Wireless Mouse",
          "quantity": 3,
          "price": 11.28
        },
        {
          "sku": "SKU-OAWSOY",
          "name": "USB Cable",
          "quantity": 4,
          "price": 186.33
        },
        {
          "sku": "SKU-77QGFF",
          "name": "Laptop Stand",
          "quantity": 3,
          "price": 193.13
        },
        {
          "sku": "SKU-8DESDD",
          "name": "Keyboard",
          "quantity": 4,
          "price": 158.7
        }
      ],
      "subtotal": 1993.35,
      "tax": 159.47,
      "total": 2152.82,
      "status": "shipped",
      "orderDate": "2026-01-25"
    },
    {
      "orderId": "ORD-0019",
      "customer": {
        "id": 19,
        "name": "Leland Kutch PhD",
        "email": "dillon.kling@hotmail.com",
        "phone": "1-814-458-1089 x3453"
      },
      "items": [
        {
          "sku": "SKU-3MHUAP",
          "name": "Wireless Mouse",
          "quantity": 1,
          "price": 49.04
        },
        {
          "sku": "SKU-VUHRDF",
          "name": "USB Cable",
          "quantity": 2,
          "price": 53.07
        },
        {
          "sku": "SKU-GD55DJ",
          "name": "Laptop Stand",
          "quantity": 3,
          "price": 117.2
        }
      ],
      "subtotal": 506.78,
      "tax": 40.54,
      "total": 547.32,
      "status": "delivered",
      "orderDate": "2026-01-14"
    },
    {
      "orderId": "ORD-0020",
      "customer": {
        "id": 20,
        "name": "Ernestine Stehr III",
        "email": "wilton.oconnell@yahoo.com",
        "phone": "742.966.4286 x514"
      },
      "items": [
        {
          "sku": "SKU-EWKHFN",
          "name": "Wireless Mouse",
          "quantity": 3,
          "price": 123.97
        }
      ],
      "subtotal": 371.91,
      "tax": 29.75,
      "total": 401.66,
      "status": "cancelled",
      "orderDate": "2026-01-13"
    },
    {
      "orderId": "ORD-0021",
      "customer": {
        "id": 1,
        "name": "Kari Schuster",
        "email": "filiberto_erdman@gmail.com",
        "phone": "1-852-296-3035 x821"
      },
      "items": [
        {
          "sku": "SKU-4XLZAF",
          "name": "Wireless Mouse",
          "quantity": 2,
          "price": 102.49
        },
        {
          "sku": "SKU-ICQREI",
          "name": "USB Cable",
          "quantity": 1,
          "price": 51.75
        }
      ],
      "subtotal": 256.73,
      "tax": 20.54,
      "total": 277.27,
      "status": "pending",
      "orderDate": "2025-11-14"
    },
    {
      "orderId": "ORD-0022",
      "customer": {
        "id": 2,
        "name": "Mr. Eduardo Flatley",
        "email": "geraldine13@gmail.com",
        "phone": "415-946-7874 x4138"
      },
      "items": [
        {
          "sku": "SKU-DELN0S",
          "name": "Wireless Mouse",
          "quantity": 3,
          "price": 14.6
        },
        {
          "sku": "SKU-5HCTAD",
          "name": "USB Cable",
          "quantity": 4,
          "price": 44.63
        },
        {
          "sku": "SKU-L6W76O",
          "name": "Laptop Stand",
          "quantity": 3,
          "price": 15.23
        },
        {
          "sku": "SKU-GBOKZO",
          "name": "Keyboard",
          "quantity": 4,
          "price": 37.92
        }
      ],
      "subtotal": 419.69,
      "tax": 33.58,
      "total": 453.27,
      "status": "processing",
      "orderDate": "2025-12-22"
    },
    {
      "orderId": "ORD-0023",
      "customer": {
        "id": 3,
        "name": "Velma Larson",
        "email": "kameron79@gmail.com",
        "phone": "1-350-849-0355"
      },
      "items": [
        {
          "sku": "SKU-APJGMV",
          "name": "Wireless Mouse",
          "quantity": 5,
          "price": 42.35
        },
        {
          "sku": "SKU-BLNOKE",
          "name": "USB Cable",
          "quantity": 2,
          "price": 185.12
        },
        {
          "sku": "SKU-GANYFS",
          "name": "Laptop Stand",
          "quantity": 3,
          "price": 184.21
        }
      ],
      "subtotal": 1134.62,
      "tax": 90.77,
      "total": 1225.39,
      "status": "shipped",
      "orderDate": "2025-12-11"
    },
    {
      "orderId": "ORD-0024",
      "customer": {
        "id": 4,
        "name": "Everett Fahey",
        "email": "darrick42@hotmail.com",
        "phone": "1-388-935-2892"
      },
      "items": [
        {
          "sku": "SKU-J5JHUI",
          "name": "Wireless Mouse",
          "quantity": 1,
          "price": 124.3
        }
      ],
      "subtotal": 124.3,
      "tax": 9.94,
      "total": 134.24,
      "status": "delivered",
      "orderDate": "2026-02-05"
    },
    {
      "orderId": "ORD-0025",
      "customer": {
        "id": 5,
        "name": "Christine Bergnaum",
        "email": "bella6@gmail.com",
        "phone": "674-237-3627 x173"
      },
      "items": [
        {
          "sku": "SKU-UPEB7T",
          "name": "Wireless Mouse",
          "quantity": 4,
          "price": 36.02
        }
      ],
      "subtotal": 144.08,
      "tax": 11.53,
      "total": 155.61,
      "status": "cancelled",
      "orderDate": "2026-02-06"
    },
    {
      "orderId": "ORD-0026",
      "customer": {
        "id": 6,
        "name": "Amanda Crona",
        "email": "dave66@gmail.com",
        "phone": "1-365-867-5838 x92727"
      },
      "items": [
        {
          "sku": "SKU-LSQLMB",
          "name": "Wireless Mouse",
          "quantity": 5,
          "price": 108.79
        },
        {
          "sku": "SKU-CAOIPN",
          "name": "USB Cable",
          "quantity": 4,
          "price": 102.17
        }
      ],
      "subtotal": 952.63,
      "tax": 76.21,
      "total": 1028.84,
      "status": "pending",
      "orderDate": "2026-01-14"
    },
    {
      "orderId": "ORD-0027",
      "customer": {
        "id": 7,
        "name": "Mrs. Stella Daugherty",
        "email": "arianna51@yahoo.com",
        "phone": "1-736-980-1661 x324"
      },
      "items": [
        {
          "sku": "SKU-TAD4NT",
          "name": "Wireless Mouse",
          "quantity": 4,
          "price": 69.75
        }
      ],
      "subtotal": 279,
      "tax": 22.32,
      "total": 301.32,
      "status": "processing",
      "orderDate": "2026-01-18"
    },
    {
      "orderId": "ORD-0028",
      "customer": {
        "id": 8,
        "name": "Roman Bogisich IV",
        "email": "elias_wolf37@gmail.com",
        "phone": "1-313-331-9100 x768"
      },
      "items": [
        {
          "sku": "SKU-RXMVBA",
          "name": "Wireless Mouse",
          "quantity": 1,
          "price": 157.3
        },
        {
          "sku": "SKU-8PU5J9",
          "name": "USB Cable",
          "quantity": 3,
          "price": 78.17
        }
      ],
      "subtotal": 391.81,
      "tax": 31.34,
      "total": 423.15,
      "status": "shipped",
      "orderDate": "2026-01-15"
    },
    {
      "orderId": "ORD-0029",
      "customer": {
        "id": 9,
        "name": "Marguerite Reinger",
        "email": "dave0@yahoo.com",
        "phone": "1-302-433-3340"
      },
      "items": [
        {
          "sku": "SKU-H492ER",
          "name": "Wireless Mouse",
          "quantity": 4,
          "price": 85.5
        },
        {
          "sku": "SKU-HK1QBP",
          "name": "USB Cable",
          "quantity": 2,
          "price": 31.6
        },
        {
          "sku": "SKU-5QGR0P",
          "name": "Laptop Stand",
          "quantity": 2,
          "price": 130.15
        },
        {
          "sku": "SKU-794RPK",
          "name": "Keyboard",
          "quantity": 2,
          "price": 40.47
        }
      ],
      "subtotal": 746.44,
      "tax": 59.72,
      "total": 806.16,
      "status": "delivered",
      "orderDate": "2026-01-25"
    },
    {
      "orderId": "ORD-0030",
      "customer": {
        "id": 10,
        "name": "Mattie Pacocha",
        "email": "eveline.emard-nienow@hotmail.com",
        "phone": "724-551-5493 x29559"
      },
      "items": [
        {
          "sku": "SKU-QZT7TH",
          "name": "Wireless Mouse",
          "quantity": 3,
          "price": 106.85
        },
        {
          "sku": "SKU-6I9ETO",
          "name": "USB Cable",
          "quantity": 4,
          "price": 53.38
        },
        {
          "sku": "SKU-7DNRW1",
          "name": "Laptop Stand",
          "quantity": 2,
          "price": 37.09
        }
      ],
      "subtotal": 608.25,
      "tax": 48.66,
      "total": 656.91,
      "status": "cancelled",
      "orderDate": "2026-01-10"
    },
    {
      "orderId": "ORD-0031",
      "customer": {
        "id": 11,
        "name": "Mr. Jake Walter",
        "email": "damian20@gmail.com",
        "phone": "691-777-4730 x3841"
      },
      "items": [
        {
          "sku": "SKU-RXCIBO",
          "name": "Wireless Mouse",
          "quantity": 1,
          "price": 157.35
        },
        {
          "sku": "SKU-DUFXJK",
          "name": "USB Cable",
          "quantity": 5,
          "price": 133.77
        }
      ],
      "subtotal": 826.2,
      "tax": 66.1,
      "total": 892.3,
      "status": "pending",
      "orderDate": "2026-01-23"
    },
    {
      "orderId": "ORD-0032",
      "customer": {
        "id": 12,
        "name": "Lance Satterfield",
        "email": "christop64@hotmail.com",
        "phone": "467-427-8351"
      },
      "items": [
        {
          "sku": "SKU-54BH9K",
          "name": "Wireless Mouse",
          "quantity": 2,
          "price": 91.28
        },
        {
          "sku": "SKU-ZLPTOL",
          "name": "USB Cable",
          "quantity": 2,
          "price": 34.18
        }
      ],
      "subtotal": 250.92,
      "tax": 20.07,
      "total": 270.99,
      "status": "processing",
      "orderDate": "2025-11-19"
    },
    {
      "orderId": "ORD-0033",
      "customer": {
        "id": 13,
        "name": "Jonathon Kuhlman",
        "email": "lorena.quigley@yahoo.com",
        "phone": "1-466-666-8061"
      },
      "items": [
        {
          "sku": "SKU-VQ3VQU",
          "name": "Wireless Mouse",
          "quantity": 5,
          "price": 169.03
        }
      ],
      "subtotal": 845.15,
      "tax": 67.61,
      "total": 912.76,
      "status": "shipped",
      "orderDate": "2026-01-27"
    },
    {
      "orderId": "ORD-0034",
      "customer": {
        "id": 14,
        "name": "Mindy Gleichner DVM",
        "email": "mavis_okuneva9@gmail.com",
        "phone": "1-656-421-2097"
      },
      "items": [
        {
          "sku": "SKU-BCHEQ6",
          "name": "Wireless Mouse",
          "quantity": 2,
          "price": 182.36
        }
      ],
      "subtotal": 364.72,
      "tax": 29.18,
      "total": 393.9,
      "status": "delivered",
      "orderDate": "2025-11-11"
    },
    {
      "orderId": "ORD-0035",
      "customer": {
        "id": 15,
        "name": "Marilyn Von",
        "email": "eduardo20@gmail.com",
        "phone": "(608) 584-3416 x183"
      },
      "items": [
        {
          "sku": "SKU-NRET6P",
          "name": "Wireless Mouse",
          "quantity": 2,
          "price": 141.83
        },
        {
          "sku": "SKU-PJVNA5",
          "name": "USB Cable",
          "quantity": 4,
          "price": 53.05
        }
      ],
      "subtotal": 495.86,
      "tax": 39.67,
      "total": 535.53,
      "status": "cancelled",
      "orderDate": "2025-12-08"
    },
    {
      "orderId": "ORD-0036",
      "customer": {
        "id": 16,
        "name": "Stephanie Hagenes",
        "email": "beryl_pollich@hotmail.com",
        "phone": "(280) 272-0072 x336"
      },
      "items": [
        {
          "sku": "SKU-XLIYON",
          "name": "Wireless Mouse",
          "quantity": 4,
          "price": 92.43
        },
        {
          "sku": "SKU-MS7RUZ",
          "name": "USB Cable",
          "quantity": 4,
          "price": 67.98
        }
      ],
      "subtotal": 641.64,
      "tax": 51.33,
      "total": 692.97,
      "status": "pending",
      "orderDate": "2026-02-07"
    },
    {
      "orderId": "ORD-0037",
      "customer": {
        "id": 17,
        "name": "Omar Witting",
        "email": "roselyn33@hotmail.com",
        "phone": "1-326-658-6662 x4127"
      },
      "items": [
        {
          "sku": "SKU-XWQV94",
          "name": "Wireless Mouse",
          "quantity": 1,
          "price": 37.18
        },
        {
          "sku": "SKU-NYAMRR",
          "name": "USB Cable",
          "quantity": 1,
          "price": 102.77
        },
        {
          "sku": "SKU-BQGJKO",
          "name": "Laptop Stand",
          "quantity": 1,
          "price": 92.44
        },
        {
          "sku": "SKU-ZFSFD9",
          "name": "Keyboard",
          "quantity": 4,
          "price": 111.97
        }
      ],
      "subtotal": 680.27,
      "tax": 54.42,
      "total": 734.69,
      "status": "processing",
      "orderDate": "2026-01-29"
    },
    {
      "orderId": "ORD-0038",
      "customer": {
        "id": 18,
        "name": "Mr. Ramiro Klein",
        "email": "linda_jerde@gmail.com",
        "phone": "758-287-3150 x056"
      },
      "items": [
        {
          "sku": "SKU-ISJ1HD",
          "name": "Wireless Mouse",
          "quantity": 2,
          "price": 79.6
        },
        {
          "sku": "SKU-SQU4LG",
          "name": "USB Cable",
          "quantity": 5,
          "price": 89.51
        }
      ],
      "subtotal": 606.75,
      "tax": 48.54,
      "total": 655.29,
      "status": "shipped",
      "orderDate": "2026-01-11"
    },
    {
      "orderId": "ORD-0039",
      "customer": {
        "id": 19,
        "name": "Ken Schiller III",
        "email": "seamus.kling@yahoo.com",
        "phone": "964.938.4785 x98776"
      },
      "items": [
        {
          "sku": "SKU-VPPAPR",
          "name": "Wireless Mouse",
          "quantity": 3,
          "price": 190.96
        }
      ],
      "subtotal": 572.88,
      "tax": 45.83,
      "total": 618.71,
      "status": "delivered",
      "orderDate": "2025-12-01"
    },
    {
      "orderId": "ORD-0040",
      "customer": {
        "id": 20,
        "name": "Randal Berge",
        "email": "hilbert6@yahoo.com",
        "phone": "280.847.5761"
      },
      "items": [
        {
          "sku": "SKU-MU4BFU",
          "name": "Wireless Mouse",
          "quantity": 4,
          "price": 182.23
        },
        {
          "sku": "SKU-MDIO8K",
          "name": "USB Cable",
          "quantity": 1,
          "price": 19.96
        },
        {
          "sku": "SKU-JXTUYT",
          "name": "Laptop Stand",
          "quantity": 1,
          "price": 98.28
        },
        {
          "sku": "SKU-C0BFDG",
          "name": "Keyboard",
          "quantity": 3,
          "price": 93.9
        }
      ],
      "subtotal": 1128.86,
      "tax": 90.31,
      "total": 1219.17,
      "status": "cancelled",
      "orderDate": "2026-01-09"
    },
    {
      "orderId": "ORD-0041",
      "customer": {
        "id": 1,
        "name": "Alan Sanford",
        "email": "nick.ratke67@gmail.com",
        "phone": "479.565.9744 x143"
      },
      "items": [
        {
          "sku": "SKU-XOQSZE",
          "name": "Wireless Mouse",
          "quantity": 1,
          "price": 61.75
        },
        {
          "sku": "SKU-L4JQK1",
          "name": "USB Cable",
          "quantity": 5,
          "price": 62.02
        }
      ],
      "subtotal": 371.85,
      "tax": 29.75,
      "total": 401.6,
      "status": "pending",
      "orderDate": "2026-02-08"
    },
    {
      "orderId": "ORD-0042",
      "customer": {
        "id": 2,
        "name": "Mr. Irvin Hills",
        "email": "kristin_fadel29@gmail.com",
        "phone": "1-808-680-4255 x770"
      },
      "items": [
        {
          "sku": "SKU-64KGTA",
          "name": "Wireless Mouse",
          "quantity": 4,
          "price": 44.19
        }
      ],
      "subtotal": 176.76,
      "tax": 14.14,
      "total": 190.9,
      "status": "processing",
      "orderDate": "2025-12-10"
    },
    {
      "orderId": "ORD-0043",
      "customer": {
        "id": 3,
        "name": "Dr. Benny Hansen",
        "email": "garth_altenwerth47@yahoo.com",
        "phone": "916-312-7046 x1021"
      },
      "items": [
        {
          "sku": "SKU-GPFAUP",
          "name": "Wireless Mouse",
          "quantity": 4,
          "price": 116.52
        },
        {
          "sku": "SKU-HNS4EG",
          "name": "USB Cable",
          "quantity": 5,
          "price": 47.77
        },
        {
          "sku": "SKU-DNL7NW",
          "name": "Laptop Stand",
          "quantity": 2,
          "price": 187.53
        }
      ],
      "subtotal": 1079.99,
      "tax": 86.4,
      "total": 1166.39,
      "status": "shipped",
      "orderDate": "2026-01-10"
    },
    {
      "orderId": "ORD-0044",
      "customer": {
        "id": 4,
        "name": "Elisa Waelchi",
        "email": "zelma.jones@gmail.com",
        "phone": "(565) 811-6458 x281"
      },
      "items": [
        {
          "sku": "SKU-S1FURD",
          "name": "Wireless Mouse",
          "quantity": 5,
          "price": 31.05
        },
        {
          "sku": "SKU-3DBLJJ",
          "name": "USB Cable",
          "quantity": 5,
          "price": 197.83
        }
      ],
      "subtotal": 1144.4,
      "tax": 91.55,
      "total": 1235.95,
      "status": "delivered",
      "orderDate": "2025-12-16"
    },
    {
      "orderId": "ORD-0045",
      "customer": {
        "id": 5,
        "name": "Warren Nienow",
        "email": "ray_kihn78@yahoo.com",
        "phone": "(927) 527-0588"
      },
      "items": [
        {
          "sku": "SKU-QA4YKZ",
          "name": "Wireless Mouse",
          "quantity": 5,
          "price": 60
        }
      ],
      "subtotal": 300,
      "tax": 24,
      "total": 324,
      "status": "cancelled",
      "orderDate": "2025-11-29"
    },
    {
      "orderId": "ORD-0046",
      "customer": {
        "id": 6,
        "name": "Miss Faye Ullrich III",
        "email": "maggie15@yahoo.com",
        "phone": "1-463-515-1766 x1578"
      },
      "items": [
        {
          "sku": "SKU-XOSGCC",
          "name": "Wireless Mouse",
          "quantity": 1,
          "price": 59.6
        },
        {
          "sku": "SKU-0GW4O7",
          "name": "USB Cable",
          "quantity": 2,
          "price": 192.13
        },
        {
          "sku": "SKU-FF5FEL",
          "name": "Laptop Stand",
          "quantity": 4,
          "price": 123.07
        }
      ],
      "subtotal": 936.14,
      "tax": 74.89,
      "total": 1011.03,
      "status": "pending",
      "orderDate": "2025-12-20"
    },
    {
      "orderId": "ORD-0047",
      "customer": {
        "id": 7,
        "name": "Lucy Miller",
        "email": "oliver19@yahoo.com",
        "phone": "1-956-614-0820 x26011"
      },
      "items": [
        {
          "sku": "SKU-FZAXHM",
          "name": "Wireless Mouse",
          "quantity": 5,
          "price": 67.86
        }
      ],
      "subtotal": 339.3,
      "tax": 27.14,
      "total": 366.44,
      "status": "processing",
      "orderDate": "2026-02-02"
    },
    {
      "orderId": "ORD-0048",
      "customer": {
        "id": 8,
        "name": "Mrs. Gladys Wolf",
        "email": "skyla16@hotmail.com",
        "phone": "1-785-383-0323 x7438"
      },
      "items": [
        {
          "sku": "SKU-2VDGMQ",
          "name": "Wireless Mouse",
          "quantity": 5,
          "price": 62.53
        },
        {
          "sku": "SKU-EYAJKF",
          "name": "USB Cable",
          "quantity": 1,
          "price": 196.47
        },
        {
          "sku": "SKU-WXGPQD",
          "name": "Laptop Stand",
          "quantity": 1,
          "price": 48.86
        },
        {
          "sku": "SKU-0N62PU",
          "name": "Keyboard",
          "quantity": 2,
          "price": 19.99
        }
      ],
      "subtotal": 597.96,
      "tax": 47.84,
      "total": 645.8,
      "status": "shipped",
      "orderDate": "2025-12-09"
    },
    {
      "orderId": "ORD-0049",
      "customer": {
        "id": 9,
        "name": "Lewis Dicki",
        "email": "toney87@gmail.com",
        "phone": "(924) 628-9074 x28927"
      },
      "items": [
        {
          "sku": "SKU-A4A5Y9",
          "name": "Wireless Mouse",
          "quantity": 1,
          "price": 79.18
        },
        {
          "sku": "SKU-AE0SAZ",
          "name": "USB Cable",
          "quantity": 1,
          "price": 66.03
        },
        {
          "sku": "SKU-WNYCP3",
          "name": "Laptop Stand",
          "quantity": 4,
          "price": 159.83
        },
        {
          "sku": "SKU-MFHFXA",
          "name": "Keyboard",
          "quantity": 1,
          "price": 119.26
        }
      ],
      "subtotal": 903.79,
      "tax": 72.3,
      "total": 976.09,
      "status": "delivered",
      "orderDate": "2026-01-03"
    },
    {
      "orderId": "ORD-0050",
      "customer": {
        "id": 10,
        "name": "Jenny Halvorson-Pagac",
        "email": "matilde.jacobson@gmail.com",
        "phone": "452-470-9131 x1866"
      },
      "items": [
        {
          "sku": "SKU-J0G4K6",
          "name": "Wireless Mouse",
          "quantity": 1,
          "price": 78.06
        }
      ],
      "subtotal": 78.06,
      "tax": 6.24,
      "total": 84.3,
      "status": "cancelled",
      "orderDate": "2025-12-15"
    }
  ]
}